sparselandtools/__init__.py
sparselandtools/learning.py
sparselandtools/pursuits.py
sparselandtools/applications/__init__.py
sparselandtools/applications/denoising.py
sparselandtools/applications/utils.py
sparselandtools/dictionaries/__init__.py
sparselandtools/dictionaries/utils.py
sparselandtools-1.0.2.dist-info/LICENSE
sparselandtools-1.0.2.dist-info/METADATA
sparselandtools-1.0.2.dist-info/WHEEL
sparselandtools-1.0.2.dist-info/top_level.txt
sparselandtools-1.0.2.dist-info/RECORD
