Metadata-Version: 2.1
Name: sparselandtools
Version: 1.0.2
Summary: A package for sparse representations and dictionary learning
Home-page: https://github.com/fubel/sparselandtools
Author: Fabian Herzog
Author-email: fabian.herzog.dev@gmail.com
License: UNKNOWN
Platform: UNKNOWN
Classifier: Programming Language :: Python :: 3
Classifier: License :: OSI Approved :: MIT License
Classifier: Operating System :: OS Independent
Requires-Python: >=3.5
Requires-Dist: alabaster (==0.7.12)
Requires-Dist: atomicwrites (==1.3.0)
Requires-Dist: attrs (==19.3.0)
Requires-Dist: Babel (==2.8.0)
Requires-Dist: bleach (==3.1.1)
Requires-Dist: brewer2mpl (==1.4.1)
Requires-Dist: certifi (==2019.11.28)
Requires-Dist: chardet (==3.0.4)
Requires-Dist: cloudpickle (==1.3.0)
Requires-Dist: cycler (==0.10.0)
Requires-Dist: Cython (==0.29.15)
Requires-Dist: dask (==2.11.0)
Requires-Dist: decorator (==4.4.1)
Requires-Dist: docutils (==0.16)
Requires-Dist: idna (==2.9)
Requires-Dist: imageio (==2.8.0)
Requires-Dist: imagesize (==1.2.0)
Requires-Dist: importlib-metadata (==1.5.0)
Requires-Dist: Jinja2 (==2.11.1)
Requires-Dist: joblib (==0.14.1)
Requires-Dist: keyring (==21.1.0)
Requires-Dist: kiwisolver (==1.1.0)
Requires-Dist: llvmlite (==0.31.0)
Requires-Dist: MarkupSafe (==1.1.1)
Requires-Dist: matplotlib (==3.1.3)
Requires-Dist: more-itertools (==8.2.0)
Requires-Dist: networkx (==2.4)
Requires-Dist: numba (==0.48.0)
Requires-Dist: numpy (==1.18.1)
Requires-Dist: packaging (==20.1)
Requires-Dist: pandas (==1.0.1)
Requires-Dist: Pillow (==7.0.0)
Requires-Dist: pkginfo (==1.5.0.1)
Requires-Dist: pluggy (==0.13.1)
Requires-Dist: prettyplotlib (==0.1.7)
Requires-Dist: py (==1.8.1)
Requires-Dist: Pygments (==2.5.2)
Requires-Dist: pyparsing (==2.4.6)
Requires-Dist: pytest (==5.3.5)
Requires-Dist: python-dateutil (==2.8.1)
Requires-Dist: pytz (==2019.3)
Requires-Dist: PyWavelets (==1.1.1)
Requires-Dist: readme-renderer (==24.0)
Requires-Dist: requests (==2.23.0)
Requires-Dist: requests-toolbelt (==0.9.1)
Requires-Dist: scikit-image (==0.16.2)
Requires-Dist: scikit-learn (==0.22.1)
Requires-Dist: scipy (==1.4.1)
Requires-Dist: seaborn (==0.10.0)
Requires-Dist: six (==1.14.0)
Requires-Dist: snowballstemmer (==2.0.0)
Requires-Dist: Sphinx (==2.4.2)
Requires-Dist: sphinxcontrib-applehelp (==1.0.1)
Requires-Dist: sphinxcontrib-devhelp (==1.0.1)
Requires-Dist: sphinxcontrib-htmlhelp (==1.0.3)
Requires-Dist: sphinxcontrib-jsmath (==1.0.1)
Requires-Dist: sphinxcontrib-qthelp (==1.0.2)
Requires-Dist: sphinxcontrib-serializinghtml (==1.1.3)
Requires-Dist: sphinxcontrib-websupport (==1.2.0)
Requires-Dist: toolz (==0.10.0)
Requires-Dist: tqdm (==4.43.0)
Requires-Dist: twine (==3.1.1)
Requires-Dist: urllib3 (==1.25.8)
Requires-Dist: wcwidth (==0.1.8)
Requires-Dist: webencodings (==0.5.1)
Requires-Dist: zipp (==3.0.0)
